st_card/__init__.py
st_card/frontend/build/asset-manifest.json
st_card/frontend/build/bootstrap.min.css
st_card/frontend/build/index.html
st_card/frontend/build/precache-manifest.8e6d8b909ddeb47ed736dcf2e8c94f14.js
st_card/frontend/build/service-worker.js
st_card/frontend/build/static/js/2.a1016b57.chunk.js
st_card/frontend/build/static/js/2.a1016b57.chunk.js.LICENSE.txt
st_card/frontend/build/static/js/2.a1016b57.chunk.js.map
st_card/frontend/build/static/js/main.200ebd9e.chunk.js
st_card/frontend/build/static/js/main.200ebd9e.chunk.js.map
st_card/frontend/build/static/js/runtime-main.3734300f.js
st_card/frontend/build/static/js/runtime-main.3734300f.js.map
streamlit_cards_templates-0.0.2.dist-info/LICENSE
streamlit_cards_templates-0.0.2.dist-info/METADATA
streamlit_cards_templates-0.0.2.dist-info/WHEEL
streamlit_cards_templates-0.0.2.dist-info/top_level.txt
streamlit_cards_templates-0.0.2.dist-info/RECORD
